{
  "file_name": "ae00027d_Doc1.pdf",
  "file_path": "d:\\Faculty Recruitment Portal\\uploads\\ae00027d_Doc1.pdf",
  "extraction_method": "ocr",
  "parsed": {
    "name": "JACK FARRELL",
    "headline": "Warehouse Worker",
    "location": "New York, NY",
    "email": "farrrellj_a689@gmail.com",
    "phone": "(718) 505-7112",
    "summary": "",
    "links": [],
    "education": [
      "10012, United States farrrellj_a689@gmail.com | October 2015 - September 2019 September 2013 - September | 2015",
      "team leaders to enhance + Monitored assembly line and"
    ],
    "skills": [],
    "experience": [],
    "publications": []
  }
}